{
"STRAS/SE": "strasse",
"STA*TD": "stadt",
"ST*EUPBG/WHA": "Tsinghua",
"SPAPB/KWROEL": "spagnol",
"SHRA/SRA": "slava",
"SHA/TKEPB/TPROEUD": "Schadenfreude",
"SHAD/TPROEUD": "Schadenfreude",
"SRAOE/TA": "vita",
"SRER/HRAG": "Verlag",
"SO*US": "sous",
"SEPL/PRE": "sempre",
"SUL": "sul",
"TKPWRAPBD/PRAOE": "grand prix",
"TKPWAEUR": "guerre",
"TKA/TKPWERB": "dagesh",
"TKAOUS/KWREPL": "deuxième",
"TKA*E": "{d'^}",
"TKA*E/KPA": "{d'^}{-|}",
"TKA*EP": "{D'^}",
"TKA*EP/KPA": "{D'^}{-|}",
"TKA*S": "Das",
"TKAS": "das",
"TK*EL": "del",
"TK*U": "du",
"TKE/HORS": "dehors",
"TKER": "der",
"TKEG/HREU": "degli",
"TPHAUPB/TKPWRA/TA": "non grata",
"TPHO/SRO": "novo",
"TPHO*US": "nous",
"TPHO*RD": "nord",
"TPHEUB/HRUPBG": "Nibelung",
"TPRA*U": "Frau",
"TPRO*U": "Frau",
"TPROEUPBD": "Freund",
"TPAO*ES": "fils",
"TPAO*UR": "für",
"KHRO*ERB": "cloche",
"KRAOEG": "krieg",
"KA/PHAOE/TPHOE": "camino",
"KAO*UR": "Coeur",
"KAOER/SKAOUR/KWRO": "chiaroscuro",
"KOPBT/RE/TEFRPS": "contretemps",
"KOPL/PA/TKRAEU": "compadre",
"KOPL/PAD/RAEU": "compadre",
"PWAOURS": "bourse",
"PHRATZ": "platz",
"PHAOU/HRAPB": "Moulin",
"PHAD/PWHA/S*EL": "mademoiselle",
"PHAD/PHA/S*EL": "mademoiselle",
"PHAD/RAEU": "madre",
"PHEZ/KWREU": "mezzi",
"PA/TER/TPA/PHEUL/KWRAS": "paterfamilias",
"PAO*U": "più",
"PAEU/KWROE/TAEU": "peyote",
"PO*R": "por",
"HRA*E": "{L'^}",
"HRA*E/KPA": "{l'^}{-|}",
"HRA*EP": "{L'^}",
"HRA*EP/KPA": "{L'^}{-|}",
"HRES/SAEU/TPAEUR": "laissez faire",
"HAU/*ER": "hauer",
"HAS/TA": "hasta",
"HAS/TA/HRA/SRAOES/TA": "hasta la vista",
"H*ER": "Herr",
"ROPB/TKO*E": "rondeau",
"RE/SHEFRPB": "recherche",
"RE/TKUBG/TOE": "reducto",
"RE/KHEFRPB": "recherche",
"REPBLG/SKWROE": "reggio",
"REBG/KWRES/AT": "requiescat",
"AUPB/PHAS": "en masse",
"AB/WEL/KWRA": "abuela",
"AL/HRA": "alla",
"*UPBD": "und",
"E/KHRAT": "eclat",
"EUPS/KWRO/TPABGT/KWRO": "ipso facto",
"EBGS/POEFT/TPABGT/KWRO": "ex post facto"
}
