{
"^STPWRAOUPBT": "obstruent",
"^SPWRAOUPBT": "obstruent",
"^TKPWHRAOUPBGS": "agglutination",
"^TKPWHRAOUPBT": "agglutinate",
"^TKW-P": "AdvP",
"STPHA*BGS": "syntax",
"STPHABGT/KHREU": "syntactically",
"STPHOPB/PHEU": "synonymy",
"SKWRA/POPB/EUBG": "Japonic",
"SKWR*ERPBG": "Germanic",
"SKWREPL/TPHAEUT": "geminate",
"SPWRAO*UFS": "intrusive",
"SHRAB/TPAEUBGS": "syllabification",
"SHAPBG/HAOEU/TPHAOES": "Shanghainese",
"SROEUFLS": "voiceless",
"SRED/EUBG": "Vedic",
"SAUB/SKWRAEU/SEPBT": "subjacent",
"SAUB/SKWRAEUS/SEU": "subjacency",
"SAUB/SKWRAEUS/*EPB/SEU": "subjacency",
"SOERB/TKPWHREUFBG": "sociolinguistic",
"SOERB/TKPWHREUFT": "sociolinguist",
"SOEPB/RAPBT": "sonorant",
"SEUPB/TABG/TEUBG": "syntactic",
"SEUPB/KROPB/EUBG": "synchronic",
"SEPL/KWROT/EUBGS": "semiotics",
"TKPWHROLT": "glottal",
"TKPWHROLT/EUBG": "glottalic",
"TKPWRA/TPAOEPL": "grapheme",
"TKPWRAF/AOEPL": "grapheme",
"TKPWRAPLT/KHREU": "grammatically",
"TKPWRAPLT/KAL": "grammatical",
"TKPWRAPLT/KALT": "grammaticality",
"TKPWRAPLT/K-L": "grammatical",
"TKPWEUPL/EL": "gimel",
"TKPWURLT": "guttural",
"TKAOEU/RAOE/SEUS": "diaeresis",
"TK*EU/TKPWHROS/KWRA": "diglossia",
"TKEF/TPHAG/REU": "Devanagari",
"TKEPL/TPHEUPL": "demonym",
"TPHAOES/EUS": "tmesis",
"TPHO/STRAT/EUBG": "Nostratic",
"TPRAEUFL": "phrasal",
"TPA/REUPBG/KWRAL": "pharyngeal",
"TPAPL/HREBGT": "familect",
"TPOEPB/TABGT/EUBG": "phonotactic",
"TPEUL/HR-LG": "philological",
"TREU/HREUPBG/WAL": "trilingual",
"TO/KHAR/KWRAPB": "Tocharian",
"KPRAP/SEUGS": "extraposition",
"KWREUPBZ": "yinz",
"KHOPL/SKAOE": "Chomsky",
"KA*LG/KA*LG": "calque",
"KOEU/TPHAEU": "koine",
"KOERPBL": "coronal",
"KOP/HRA": "copula",
"PWAOU/SROF/TKOPB": "boustrophedon",
"PWABG/RO/TPHEUPL": "backronym",
"PHRAOE/TPHAFPL": "pleonasm",
"PHRAOE/TPHAFT": "pleonast",
"PHRAT/TKOEUFP": "Plattdeutsch",
"PHROE/SEUF": "plosive",
"PHROES/EUF": "plosive",
"PHRU/P-FRT": "pluperfect",
"PHO*EUT/THEUS": "metathesis",
"PHOER/TPAOEPL": "morpheme",
"PRO*EUT/SKPOE/AO*URPB": "Proto-Indo-European",
"PAOEUD/PAOEUP": "pied-pipe",
"PAOEUD/PAOEUPG": "pied-piping",
"PAOEUD/PAOEUPS": "pied-pipes",
"PAOEUD/PAOEUPD": "pied-piped",
"POEUL/SAOEPL": "polyseme",
"PEUPB/KWREUPB": "pinyin",
"WH*/TPROPBT": "wh-front",
"WH*/KHRAUS": "wh-clause",
"W*UG": "wug",
"WUGS": "wugs",
"HRA/PWO*EF": "Labov",
"HRAOU/KWRAPB": "Luwian",
"HRAOPB/WORD": "loanword",
"HRAEUBL/AOEUZ": "labialize",
"HROEBG/TEUF": "locative",
"HROPBLG/PWAPB": "Lojban",
"HR*EBGT": "lect",
"HRE/TPHAOEUT": "lenite",
"HRE/TPHEUGS": "lenition",
"HREUPBG/WEU/SAO*EUD": "linguicide",
"HREUPBG/WEU/SAOEUD": "linguicide",
"HAPB/SKWRA": "hanja",
"HEUPBG/HREURB": "Hinglish",
"RAO*EUPL": "rime",
"ROET/SAOEUDZ": "rhotacized",
"ROET/SAOEUZ": "rhotacize",
"ROET/SEUFPL": "rhotacism",
"ROET/SEUFT": "rhotacist",
"RERT/TPHEUPL": "retronym",
"AOEU/KWREUPB": "ayin",
"AOU/TPOPB/EUBG": "euphonic",
"AF/REU/KAPBS": "Afrikaans",
"AFL/KWROERL": "alveolar",
"AR/TEUBG/HRA/TOER": "articulatory",
"APBG/HREURB": "Anglish",
"AL/TPOPB/KHREU": "allophonically",
"AL/TPOPB/EUBG": "allophonic",
"AL/TAEU/EUBG": "Altaic",
"AL/TAEUBG": "Altaic",
"AS/TPHAPBT": "assonant",
"AD/TPHOPL/TPHAL": "adnominal",
"OPT/PHALT": "optimality",
"EUD/KWRO/TKPWRAPL": "ideogram",
"ERG/TEUF": "ergative",
"ERG/TEUFT": "ergativity",
"EBGS/KREFPBS": "excrescence",
"ET/PHOPB": "etymon"
}
