{
"STAFL/KOBG/US": "staphylococcus",
"SKWRE/SKWRAOU/TPHUPL": "jejunum",
"SKWREPB/TO/AOUR/TPHAER": "genitourinary",
"SKORB/AOUT/EUBG": "scorbutic",
"SPHRE/TPHEBGT/PHEU": "splenectomy",
"SROESZ": "cirrhosis",
"SREU/SREUP/ROUS": "viviparous",
"SRER/TEUPBLG/TPHOUS": "vertiginous",
"SAOEU/TOE/SEUS": "cytosis",
"SE/TAEURBS": "setaceous",
"SEUR/ROESZ": "cirrhosis",
"SUP/RAEUGS": "suppuration",
"TKPWHRAOE/OE/PHA": "glioma",
"TKPWAFT/RAOEUTS": "gastritis",
"TKAOEU/PHROEUD": "diploid",
"TKAOEUL/TOER": "dilatory",
"TKABGT/HREUFPL": "dactylism",
"TPHRALG/KWRA": "neuralgia",
"TPHAOUR/STHAOEPB/KWRA": "neurasthenia",
"TPHAOUR/AL/SKWREUBG": "neuralgic",
"TPHAOUR/ALG/EUBG": "neuralgic",
"TPHAOURLG/KWRA": "neuralgia",
"TPHAOURS/THAOEPB/KWRA": "neurasthenia",
"TPHAOUBG/HRAOE/OEL/US": "nucleolus",
"TPHAOUBG/HRAOE/OELS": "nucleolus",
"TPHAOUBG/HROELS": "nucleolus",
"TPEUPL/PWRAEUT": "fimbriate",
"TPEB/RAOEUL": "febrile",
"TRAOEUP/TPOEB/KWRA": "trypophobia",
"TE/TPHES/PHUS": "tenesmus",
"KHOL/REUBG": "choleric",
"KREUL/KWRUPL": "cilium",
"KRUR/A*L": "crural",
"KA/ROTD": "carotid",
"KARD/KWROEUD": "cardioid",
"KAL/KAEUPB/KWR*US": "calcaneus",
"KAL/KAEUPB/KWRUS": "calcaneus",
"KORT/KAEUGS": "cortication",
"KORT/KAEUT": "corticate",
"KOBGS/EUPBLG/KWRAL": "coccygeal",
"KOL/REUBG": "choleric",
"PWHRAS/TOE/PHA": "blastoma",
"PWHREUPL/KWRA": "bulimia",
"PWEPB/SO*E": "benzo",
"PHAOEU/SAOEL/KWRUPL": "mycelium",
"PHAOEU/KARD/KWRUPL": "myocardium",
"PHAOED/KWRAFT/TPHUPL": "mediastinum",
"PHE/TPHEUS/KUS": "meniscus",
"PA/R*EPBG/PHA": "parenchyma",
"POEL/KWROE/PHAOEUL/AOEUTS": "poliomyelitis",
"PER/KARD/KWRAL": "pericardial",
"HRA/KREU/PHAL": "lacrimal",
"HRAEURPBLG/AOEUTS": "laryngitis",
"HREP/SEUS": "lepsis",
"HREP/TKOPT/RA": "Lepidoptera",
"HREPS/EUS": "lepsis",
"HAOEURP/ES/THAOES/KWRA": "hyperesthesia",
"H*PLG": "HMG",
"RA/KAOEUT/EUBG": "rachitic",
"RA/KAOEUTS": "rachitis",
"A/TRO/PAOEPB": "atropine",
"A/PAOER/KWREPBT": "aperient",
"A/PER/KWREPBT": "aperient",
"AEUR/KWROE/HRAR": "areolar",
"AL/PWAOUPL/*EPB": "albumen",
"EUS/KAOE/PHEUBG": "ischemic",
"EPBD/KWRO/TKERPL": "endoderm",
"EL/TPAPBT/AOEU/SEUS": "elephantiasis"
}
