{
"STRAOEUT": "striate",
"SKWROEUS/HREU": "joyously",
"SHAO*EUR": "shyer",
"TKAOEU/SAOES": "diocese",
"TKAOEFBGS": "deification",
"TKAOEBGT/SRAEUT": "deactivate",
"TKO*EUPB": "doyen",
"TPHAOEL/SKWREUFPL": "neologism",
"PWOEURB": "boyish",
"PWEL/KWRAEUBG": "bellyache",
"PHAOEUP/KWRA": "myopia",
"PHAOEUS/PHA": "miasma",
"PHAOEUS/PHA/TA": "miasmata",
"PHAOEPB/TKER": "meander",
"PHE/HREUF/HROUS": "mellifluous",
"PHEUPB/WEPBD": "minuend",
"PRAOEPLGS": "preemption",
"PRAOEPLT": "preempt",
"WAEU/SAOEZ": "oases",
"WAEU/SEUS": "oasis",
"WAEUS/EUS": "oasis",
"WAEUSZ": "oasis",
"HE/PWRA*EUBG": "Hebraic",
"RAOEPB/KARPB/AEUGS": "reincarnation",
"RAOUPB/KWROPB": "reunion",
"RE/KRAOELGS": "recreational",
"REBG/RAOELGS": "recreational",
"REBG/RAOEGS": "recreation",
"AOE/TKPWOEUFPL": "egoism",
"AOE/TKPWOEUFT": "egoist",
"AR/KAEUFPL": "archaism"
}
