{
"2340": "No.",
"34*EU9": "MIT",
"^SP*PB": "ESPN",
"^TK-BG": "IDK",
"STKPW*FRL": "SGML",
"STPH*PB": "CNN",
"SKWR/SO*PB": "json",
"SKWR/PEG": "jpeg",
"SKWROFPB": "json",
"SKWREPG": "jpeg",
"SKUZ/KWREU": "SCSI",
"SPH*PT": "SMTP",
"SPH-FD": "SMH",
"SPH-PT": "SMTP",
"SA*UP": "USA",
"S*ERPB": "CERN",
"SET/KWREU": "SETI",
"S-TD": "STD",
"TKPWR*EU": "FYI",
"TKPWO*P": "GOP",
"TKPW*PT": "GPT",
"TKPW-PD": "GDP",
"TKAUPL": "DOM",
"TKAR/PA": "DARPA",
"TKARP/KWRA": "DARPA",
"TK*RD": "DDR",
"TK-R": "Dr.",
"TK-PLZ": "DMZ",
"TPWH": "TBH",
"TPHAO*EUPD": "NYPD",
"TPHO*E": "No.",
"TPH*BS": "NBC",
"TPA*RBG": "FARC",
"TH*PT": "HTTP",
"T*PBT": "TNT",
"KP-FRL": "XML",
"KP-FLT": "XSLT",
"KP-BGSD": "XKCD",
"KWRAO*EP": "IEEE",
"KWRAEUPLS": "YMCA",
"KWRAFRL": "YAML",
"KWRO*EPB": "IDK",
"KWAO*EUS": "ICQ",
"KRAO*EP": "CEO",
"KRO*R": "OCR",
"KR*E": "CE",
"KR*BS": "CBS",
"KR*D/H-F/ROPL": "CD-ROM",
"KAT/KAT": "CAT",
"K-PL": "km",
"PWAO*ES": "BCE",
"PW*BS": "BBC",
"PW*S": "BC",
"PW-RB": "BRB",
"PW-BS": "BBS",
"PH/PH": "pH",
"PH/PHEG": "MPEG",
"PH/PEG": "MPEG",
"PH*FP": "MVP",
"PH*FPB": "MSN",
"PH*R": "Mr.{-|}",
"PH*PB": "Minnesota",
"PHEUT/PHEUT": "MIT",
"PR*P": "PR",
"P*BS": "PBS",
"P-PBG": "PNG",
"WEUS/KWREU/WEUPL": "WYSIWYM",
"WEUS/KWREU/WEUG": "WYSIWYG",
"W-FT": "wtf",
"W-BT": "btw",
"HR*LS": "LLC",
"HR-FG": "LFG",
"HR-BGT": "LGBT",
"H*PS": "HS",
"H-PT": "HTTP",
"H-PTS": "HTTPS",
"R*EUFBG": "RISC",
"AO*EURBG": "IIRC",
"AO*EURS": "IRC",
"AO*L": "AOL",
"AOEURL": "IRL",
"AOEPB/KWRABG": "ENIAC",
"A*EUPT": "ATP",
"A*EUPD": "AD",
"A*FBG": "AFK",
"O*EUF": "UFO",
"O*EP": "Op.",
"O*PLG": "OMG",
"*ERP": "ER",
"*UPB": "UN",
"*UPS": "UPS",
"*US/*US/*US": "United States of America",
"*US/*US/*US/*US": "USA",
"*US/-F/A*": "United States of America"
}
