{
"STKAO*ES": "decease",
"STKEUPB": "destine",
"STKEPBL": "incidental",
"STKEPBT": "incident",
"STKEPBTS": "incidents",
"STKEPBS": "incidence",
"STPH": "is in",
"STPHAOD": "understood",
"STPHEUBL": "sensible",
"STPHEUBLT": "sensibility",
"STPHEUBG/*ER": "snicker",
"STPH-T": "is in the",
"STPA": "sfa",
"STROEUD": "steroid",
"STA*R": "tsar",
"STAEUGS/A*ER": "stationery",
"STO*EUD": "studio",
"STEUPLGS": "stipulation",
"STEUPLT": "stipulate",
"STERLGZ": "sterilizing",
"SKPOEFR": "and over",
"SKPOUT": "and out",
"SKPOPB": "and on",
"SKPEPBD": "and end",
"SKWRO*PB": "Jon",
"SKWROBGS": "jocks",
"SKWR*EF": "Geoff",
"SKWRET/SO*PB": "Jetson",
"SKWRUPL": "jum",
"SKWEULGS": "squiggles",
"SKRAO*EUT": "scythe",
"SKAOEUPB": "consign",
"SKOEL": "console",
"SKOUS": "Scouse",
"SPWROUBGS": "introduction",
"SPWROG": "interrog",
"SPWAOUS": "enthuse",
"SPWEPBLGS": "intentional",
"SPRAOET": "spreadsheet",
"SPREUPBLG": "sprinkle",
"SHRAOEUGT": "slighting",
"SHROE/TKEUPBG/*ER": "Schrödinger",
"SHAPB/TPHOPB": "Shannon",
"SHEUT/SAO*U": "Shih Tzu",
"SRAOED": "recede",
"SRAL/KEU/REU": "Valkyrie",
"SRERBGTS": "vectors",
"SREPBG": "venge",
"SR-S": "vs.",
"SAO*E": "zee",
"SAO*EUD/KOE": "zydeco",
"SAO*EPBT": "zenith",
"SAO*ED": "cede",
"SAO*UT": "suite",
"SAOE/SAR": "Caesar",
"SAOUBL": "suitable",
"SAOUBLT": "suitability",
"SAUPB/TKER": "Saunder",
"SALD": "sadly",
"S*EUP/HROBG": "Ziploc",
"S*EUS/HREU": "Cicely",
"S*EF": "{^self}",
"S*EFL": "{self^}",
"S*ELS": "zealous",
"SEUPB/KRET/EUBG": "syncretic",
"SEUS/HREU": "Sicily",
"SEFRBT": "servant",
"SEFL": "self",
"SEBGTS": "sects",
"TKPWHRAOEUS/AOEPB": "glycine",
"TKPWHRAEUT": "congratulate",
"TKPWHRASZ": "glasses",
"TKPWRA*EF": "gravy",
"TKPWRAEUL": "grail",
"TKPWRAEF": "{^graphy}",
"TKPWREUZ/HREU": "grizzly",
"TKPWA/TOE": "gateau",
"TKPWAS/HRAOEUGT": "gaslighting",
"TKPWOLD": "gold",
"TKPWEUB": "gib",
"TKWERGT": "diverting",
"TKHRO*G": "dialogue",
"TKHROG": "dialog",
"TKHREURBGS": "deliberation",
"TKRAO*EUF/-BL": "derivable",
"TKRESZ": "dresses",
"TKRUPBLG": "drudge",
"TKR-T": "doctorate",
"TKAO*US": "deuce",
"TKAOEFT": "deviate",
"TKAOUBG/A*L": "ducal",
"TKA*RT": "Darth",
"TKA*D": "Dad",
"TKAEURPBG": "danger",
"TKOEUR": "diary",
"TKOEPBLG": "doge",
"TKEUPBG/KWREU": "dinghy",
"TKEUBGS": "diction",
"TKEULG": "digital",
"TPHRAOEUR": "flyer",
"TPHRART": "familiarity",
"TPHRABGS": "flax",
"TPHREPBT": "plenty of",
"TPHRUL": "fully",
"TPHAOERB": "nearby",
"TPHA*E": "neigh",
"TPHAEFT": "nasty",
"TPHAER": "{^inary}",
"TPHO*EUPB": "neon",
"TPHO*EL": "Noel",
"TPHOELS": "Knowles",
"TPHOES": "knows",
"TPHOEZ": "nose",
"TPHOUPBS": "nouns",
"TPHOFPB": "none of",
"TPHORB": "nosh",
"TPHUFRB": "numb",
"TPH-R": "under",
"TPH-RPT": "inspector",
"TPH-P": "NP",
"TPH-PB": "underneath",
"TPH-GTS": "noticing",
"TPREUDZ": "Fridays",
"TPAO*EUT": "{^phyte}",
"TPAOEPBGS": "phoenix",
"TPARBGS": "fabrication",
"TPABLGT": "faculty",
"TPOEUPBT": "fountain",
"TPEUL/HREUP": "Phillip",
"TP-S": "ifs",
"THROPBGS": "throngs",
"THOU": "thou",
"TRAPBS": "{trans^}",
"TRAPBS/TKPWREFR": "transgressor",
"TRAPBZ": "trans",
"TRU": "true",
"TAOEU/ROE": "tyro",
"TAOEURT": "tighter",
"TA*BGS": "tacks",
"TAEURPBS": "containers",
"TO*ED": "toed",
"TOEPL": "tome",
"TOED": "towed",
"TORB": "tosh",
"T*ERT": "tether",
"T-PBT": "continuity",
"KPHAOUPB/EUFT": "communist",
"KPHEPLT": "commencement",
"KPRAEU": "X-ray",
"KPARPBD": "Alexander",
"KWRAO*EU": "{^ae}",
"KWRURPB": "European",
"KWRUPBG/HREUPBG": "youngling",
"KWAELT": "quietly",
"KW*ERT": "QWERTY",
"KHRAOER/K*UT": "clear-cut",
"KHRAFD": "classified",
"KHOEPB": "chosen",
"KRAOUT": "recruit",
"KRAOUS/TPORPL": "cruciform",
"KRAEUBGS": "contradiction",
"KROSZ": "crosses",
"KR*EUBGT": "cricket",
"KREUFPB": "christen",
"KREULG": "critical",
"KREBL": "credible",
"KAOEUPBLD": "kindly",
"KAOEPBT": "continent",
"KAOG": "consisting",
"KA*EUPBS": "Keynes",
"KAUFL/HREU": "causally",
"KAUPB/TPHRAEUT": "conflate",
"KAUPBG/TKPWAEUGS": "congregation",
"KAT/HROGS": "catalogs",
"KO*URPBT": "{counter^}",
"KOURPBT": "counter",
"KOFRT": "covert",
"KOPL/TPHEUFT": "communist",
"KEUSZ": "kisses",
"KEUD/TPHAPG": "kidnapping",
"KULD": "culled",
"K-FRPBGT": "confronting",
"K-FRPBGS": "confrontation",
"K-FL": "confidential",
"PWRAOD": "brood",
"PWALT/PHOR": "Baltimore",
"PWO*RB": "Bosch",
"PWORB": "bosh",
"PWOSZ": "bosses",
"PWEUBL/K-L": "biblical",
"PHRA/TOPB/EUBG": "platonic",
"PHRAO*EPBS": "Marines",
"PHRA*S": "palace",
"PHRAEU/SHA": "Malaysia",
"PHAOERD": "myriad",
"PHAOR": "moor",
"PHAEUB": "may be",
"PHAR/SAEU": "Marseille",
"PHAPB/SKWRU/PHEUT": "manumit",
"PHAPBL": "manual",
"PHAPBLS": "manuals",
"PHO*RT": "mort",
"PHOEUD": "media",
"PHOERPB/EUFT": "modernist",
"PHOFRPBT": "monster",
"PHORT/-D": "imported",
"PHOLDZ": "models",
"PH*EUBG": "mechanic",
"PHEUFPLT": "manipulative",
"PHEFRPB/TKAOEUZ": "merchandise",
"PHEPL/WAR": "memoir",
"PHURL": "mural",
"PHULG": "mulling",
"PROF/SEU": "prophecy",
"PROF/SEUS": "prophecies",
"PRE/SEPBT/*PLT": "presentiment",
"PREUBG/-S": "pricks",
"PA/PA": "papa",
"PA*EUPB": "Paine",
"PAEURPBT": "painter",
"PAEURPBTS": "painters",
"PARBT": "passionate",
"PASZ": "passes",
"P*ERPBLG": "personage",
"PEL": "pell",
"WHAOEUD": "why'd",
"WHEUR": "whirr",
"WOEU": "would I",
"WOEFL": "woeful",
"WOR/SHEUPD": "worshipped",
"WEUL/KEUPB": "Wilkin",
"WUPBS": "ones",
"HRAO*EUBG": "{^like}",
"HRAO*EGS": "legion",
"HRAOEUBL/OUS": "libelous",
"HRA*/HRA*": "Los Angeles",
"HRA*EBG": "{,}like{,}",
"HRAFPLT": "harassment",
"HRO*ES": "loess",
"HROSZ": "losses",
"HR*EFR": "lesser",
"HAO*EL": "heel",
"HAOEL": "he'll",
"HA*F": "{half-^}",
"HAPB/TPHA": "Hannah",
"HOUZ": "how's",
"H*ERT": "heather",
"HURPBT": "hunter",
"HUBG/*L": "huckle",
"RAOERD": "reared",
"RAOEGD": "reading",
"RAOUB/KWREU": "ruby",
"RA*EUPBG": "rank",
"RAEUR/TPAOEUD": "rarefied",
"RAEUPLD": "remained",
"RAERT": "rather the",
"RAEL/TOR": "realtor",
"RAURD": "reward",
"RAF": "raff",
"ROLS/ROEUS": "Rolls-Royce",
"REPT/EUFS": "representatives",
"RUF/KWRAPB": "ruffian",
"AO*URPB": "European",
"AOEFS/TKROP": "eavesdrop",
"A*EUPBT/PAOEU/RET/EUBG": "antipyretic",
"A*UBGS": "aux",
"A*FP": "asp",
"A*FPLT": "{&A.}",
"A*FT": "aft",
"A*G": "ag",
"AEUPBL": "alien",
"AEUGD": "aiding",
"AEUD/*EPB": "Aiden",
"AED": "ade",
"ARBGS": "arbitration",
"APBG/HRO": "{Anglo^}",
"APL/TPHEFT/KWREU": "amnesty",
"APL/PHEU": "{amphi^}",
"APLS": "ams",
"OEUR": "euro",
"OUP": "occupy",
"OPL/HR*ET": "omelette",
"OB": "ob",
"*ETS": "et cetera",
"EURBGD": "irked",
"EUPB/SEPBT": "innocent",
"EFPBS": "essence",
"EFBG": "{^esque}",
"ETS": "etc.",
"UPBDZ": "underside",
"-GS": "{^ing}{^s}"
}
