{
"STKRABGD": "distracted",
"SKAOETD": "succeeded",
"SPOPBTD": "responded",
"SROUPBTD": "surrounded",
"SOUPBTD": "sounded",
"TKPWRA*TD": "graduated",
"TKPWROUPBTD": "grounded",
"TKPWAOEUTD": "guided",
"TKAEUBGD": "educated",
"TPWHAEUTD": "invaded",
"TPOUPBTD": "founded",
"TPORG/-D": "forgotten",
"TPORGD": "forgotten",
"KPHRAOUTD": "excluded",
"KPHAOUBGD": "communicated",
"KWEUBGD": "convicted",
"KRUBGD": "constructed",
"KUBGD": "conducted",
"PWHREUGD": "obligated",
"PWOUPBTD": "bounded",
"PHAOEUPBTD": "minded",
"PROEUFTD": "provided",
"PER/SWAEUTD": "persuaded",
"WOUPBTD": "wounded",
"HAPBTD": "handed",
"ROUPBTD": "rounded",
"REUBGD": "restricted",
"ORTD": "ordered",
"EPBTD": "ended",
"UPB/KP-PD": "unexpected"
}
