{
"STKPRAFRPBS": "disenfranchise",
"STKOEURPBGS": "disorientation",
"STKOEURPBT": "disorient",
"STKOERPBGS": "disorientation",
"STKOERPBT": "disorient",
"SKPROEUD": "android",
"SKP*EUPBG": "and I don't think",
"SKP*EUBG": "and I think",
"SKPEPB": "and then",
"SKEUFT": "scientist",
"SPWO": "into",
"SPHAORB": "smoosh",
"SEURBG/SREPBGS": "circumvention",
"SEURD": "consider",
"TKPHARBGT": "demarcate",
"TKPHARBGS": "demarcation",
"TKUFRPLG": "dumpling",
"TPRER": "from her",
"TPAGT": "fact",
"THRERPBS": "tolerance",
"THRERT": "tolerate",
"TRAPBSZ": "trance",
"KAOEUF": "kind of",
"KAUPB/TPHRAG/RAEUGS": "conflagration",
"KUFPB": "cousin",
"PHRAOPB": "maroon",
"POF": "point of view",
"HAOUFRLG": "humiliating",
"HAOUFRLGS": "humiliation",
"HAOUFRLT": "humiliate",
"AFRBGS": "ambition",
"ARBLT": "arbitrarily"
}
