{
"STKPWRAOET": "integrity",
"STKRAOU": "construe",
"STKAOEUZ": "standardize",
"STPHUFP": "inasmuch",
"STPAOELT": "facility",
"STRART": "restart",
"STROR": "restore",
"STRORGS": "restoration",
"SKWRAPLT": "gentleman",
"SKWREPLT": "gentlemen",
"SKRAOEPBT": "screenshot",
"SKREUF": "sacrifice",
"SPWRAOU": "interview",
"SPWRAOUF": "interview",
"SPWRAOUFR": "interviewer",
"SPWRAOUR": "interviewer",
"SPWRAUF": "interview",
"SPWAOET": "entity",
"SPWEFRPBG": "interchange",
"SPHAER": "summary",
"SHRAER": "salary",
"SHRERB": "celebrate",
"SHRERBGS": "celebration",
"SROEUPB": "violin",
"SAO*ERB": "seizure",
"TKPWHRAER": "gallery",
"TKPWRURLT": "agriculture",
"TKPHREUPB": "Mandarin",
"TKPHEUF": "administrative",
"TKHRAO*EUPB": "decline",
"TKAEURB": "Danish",
"TPWEL": "farewell",
"TPHROERPL": "formulae",
"TPHREUFL": "fulfill",
"TPHRUFL": "fulfill",
"TPH*RDZ": "insider",
"TPHEURB": "finish",
"TPRAOEPBLS": "freelance",
"TPRAPBL": "frankly",
"TPO*EULT": "filthy",
"TPOERGD": "foreground",
"THREURGS": "transliteration",
"THREURT": "transliterate",
"THUPBL": "thumbnail",
"TRAEURBG": "trademark",
"T*ELG": "technical",
"TEPL": "temperature",
"KPHRAR": "exemplar",
"KWRAOUFL": "youthful",
"KWAOEPD": "Wikipedia",
"KWAFPB": "quantify",
"KWEPBL": "consequential",
"KWEPBLT": "consequently",
"KWEPBT": "consequent",
"KHREUFT": "catalyst",
"KRAOEBGT": "critique",
"KROEUFG": "increasing",
"KROFRD": "crossword",
"KAUPLT": "contemplate",
"KEFRPLT": "contemplate",
"KUFLT": "cultivate",
"PWRAEUP": "breakup",
"PWAORBG": "bookmark",
"PHRA*EULS": "playlist",
"PHRAEUGD": "playground",
"PHRAUR": "popular",
"PHRAURT": "popularity",
"PHRAUPLT": "platinum",
"PHAOEPBT": "meantime",
"PHABGSZ": "maximize",
"PHO*B": "impossible",
"PHOEUFRP": "moisture",
"PHOBL": "impossibly",
"PHOBLT": "impossibility",
"PHEUPLZ": "minimize",
"PHEFGS": "manifestation",
"PHEFT": "manifest",
"PHELG": "mechanical",
"PRAEL": "principally",
"WHRAOER": "volunteer",
"WHROEP": "envelope",
"WRERS": "reverse",
"HROELG": "locally",
"HAOEURB": "Hebrew",
"HOEURPBG": "hungry",
"RAOEPGS": "reception",
"RAUF": "review",
"RAUFR": "reviewer",
"ROFGS": "resolution",
"R*EPLD": "remedy",
"REFPGS": "reception",
"AOUFPB": "unify",
"AOUFPBGS": "unification",
"AOURPL": "username",
"A*EURPL": "airplane",
"OFBLS": "oblivious",
"*EFLD": "evidently"
}
